Metadata-Version: 2.1
Name: python-gelbooru
Version: 0.1.1
Summary: Python-Gelbooru is an unofficial and lightweight asynchronous wrapper for the Gelbooru API.
Home-page: https://github.com/4gboframram/Python-Gelbooru
Author: 4gboframram
License: gpl-3.0
Keywords: gelbooru,anime,artwork,anime artwork,booru
Platform: UNKNOWN
Classifier: Development Status :: 4 - Beta
Classifier: Intended Audience :: Developers
Classifier: Topic :: Multimedia :: Graphics
Classifier: Topic :: Software Development :: Libraries :: Python Modules
Classifier: License :: OSI Approved :: GNU General Public License v3 (GPLv3)
Classifier: Programming Language :: Python :: 3.9
